airflow_cust_base/__init__.py
airflow_cust_base/gdrive_file_processing.py
airflow_cust_base-0.0.1.dist-info/METADATA
airflow_cust_base-0.0.1.dist-info/WHEEL
airflow_cust_base-0.0.1.dist-info/top_level.txt
airflow_cust_base-0.0.1.dist-info/RECORD
