Metadata-Version: 2.1
Name: airflow-cust-base
Version: 0.0.1
Summary: Gdrive auth and list drive package
Home-page: UNKNOWN
Author: Simona
License: UNKNOWN
Keywords: python,gdrive
Platform: UNKNOWN
Classifier: Development Status :: 3 - Alpha
Classifier: Programming Language :: Python :: 3
Classifier: Operating System :: MacOS :: MacOS X
Classifier: Operating System :: Microsoft :: Windows
Requires-Dist: oauth2client
